yacfg/__init__.py
yacfg/cli_arguments.py
yacfg/config_data.py
yacfg/exceptions.py
yacfg/files.py
yacfg/logger_settings.py
yacfg/meta.py
yacfg/output.py
yacfg/profiles/_libs/utils.jinja2
yacfg/profiles.py
yacfg/query.py
yacfg/templates/libs/headers/config_header.jinja2
yacfg/templates/libs/headers/generator_notice.jinja2
yacfg/templates/libs/headers/properties_headers.jinja2
yacfg/templates/libs/headers/xml_header.jinja2
yacfg/templates/libs/licenses/apache-2.0/config.jinja2
yacfg/templates/libs/licenses/apache-2.0/plaintext.jinja2
yacfg/templates/libs/licenses/apache-2.0/properties.jinja2
yacfg/templates/libs/licenses/apache-2.0/xml.jinja2
yacfg/templates/libs/utils.jinja2
yacfg/templates.py
yacfg/yacfg.py
yacfg/yacfg_cli.py
yacfg_batch/__init__.py
yacfg_batch/cli_arguments.py
yacfg_batch/exceptions.py
yacfg_batch/meta.py
yacfg_batch/yacfg_batch.py
yacfg_batch/yacfg_batch_cli.py
yacfg-0.9.4.dist-info/entry_points.txt
yacfg-0.9.4.dist-info/LICENSE
yacfg-0.9.4.dist-info/WHEEL
yacfg-0.9.4.dist-info/METADATA
yacfg-0.9.4.dist-info/RECORD
