Metadata-Version: 2.1
Name: yacfg
Version: 0.9.4
Summary: Template based configuration files generator based on jinja2 and yaml.
Home-page: https://github.com/rh-messaging-qe/yacfg
License: Apache-2.0
Author: Zdenek Kraus
Author-email: zkraus@redhat.com
Maintainer: Dominik Lenoch
Maintainer-email: dlenoch@redhat.com
Requires-Python: >=3.7,<4.0
Classifier: Development Status :: 4 - Beta
Classifier: Environment :: Console
Classifier: Intended Audience :: Developers
Classifier: Intended Audience :: System Administrators
Classifier: License :: OSI Approved :: Apache Software License
Classifier: Operating System :: MacOS
Classifier: Operating System :: Microsoft :: Windows
Classifier: Operating System :: POSIX
Classifier: Programming Language :: Python :: 3
Classifier: Programming Language :: Python :: 3.10
Classifier: Programming Language :: Python :: 3.7
Classifier: Programming Language :: Python :: 3.8
Classifier: Programming Language :: Python :: 3.9
Classifier: Topic :: Software Development :: Code Generators
Classifier: Topic :: Software Development :: Libraries :: Python Modules
Classifier: Topic :: Software Development :: Testing
Classifier: Topic :: System :: Installation/Setup
Classifier: Topic :: System :: Systems Administration
Classifier: Topic :: Text Processing
Classifier: Topic :: Utilities
Provides-Extra: color_log
Requires-Dist: PyYAML (>=6.0,<7.0)
Requires-Dist: colorama (>=0.4.4,<0.5.0); extra == "color_log"
Requires-Dist: colorlog (>=5.0.1,<7.0.0); extra == "color_log"
Requires-Dist: importlib-metadata (<4.8.1); python_version < "3.8"
Requires-Dist: jinja2 (>=3.1.2,<4.0.0)
Requires-Dist: jinja2-ansible-filters (>=1.3.2,<2.0.0)
Project-URL: Bug Tracker, https://github.com/rh-messaging-qe/yacfg/issues
Project-URL: Documentation, https://rh-messaging-qe.github.io/yacfg/
Project-URL: Repository, https://github.com/rh-messaging-qe/yacfg.git
